dryades/__init__.py
dryades/const.py
dryades/bimfile/__init__.py
dryades/bimfile/bimfile.py
dryades/btreecore/__init__.py
dryades/btreecore/btcore.py
dryades/btreecore/btnode.py
dryades/btreecore/btnodelist.py
dryades/btreecore/conv.py
dryades/btreecore/hexdump.py
dryades/btreeplus/__init__.py
dryades/btreeplus/bptree.py
dryades/dllfile/__init__.py
dryades/dllfile/dllist.py
dryades/dllfile/hexdump.py
dryades/fdlock/__init__.py
dryades/fdlock/backend.py
dryades/fdlock/lock.py
dryades/heapfile/__init__.py
dryades/heapfile/heap.py
dryades/heapfile/hexdump.py
dryades-0.0.1.dist-info/LICENSE.md
dryades-0.0.1.dist-info/METADATA
dryades-0.0.1.dist-info/WHEEL
dryades-0.0.1.dist-info/top_level.txt
dryades-0.0.1.dist-info/RECORD
