Metadata-Version: 2.1
Name: dryades
Version: 0.0.1
Summary: dryades umbrella project
Home-page: https://github.com/kr-g/dryades
Author: k. goger
Author-email: k.r.goger+dryades@gmail.com
License: AGPLv3+
Project-URL: Issues, https://github.com/kr-g/dryades/issues
Keywords: python3,base tools
Classifier: Development Status :: 3 - Alpha
Classifier: Operating System :: POSIX :: Linux
Classifier: Environment :: Console
Classifier: Topic :: Utilities
Classifier: Topic :: Software Development :: Libraries :: Python Modules
Classifier: Intended Audience :: Developers
Classifier: Intended Audience :: Information Technology
Classifier: Intended Audience :: Other Audience
Classifier: Programming Language :: Python :: 3
Classifier: License :: Free For Home Use
Classifier: License :: Free for non-commercial use
Classifier: License :: Free To Use But Restricted
Classifier: License :: OSI Approved :: GNU Affero General Public License v3 or later (AGPLv3+)
Classifier: License :: Freely Distributable
Requires-Python: >=3.8
License-File: LICENSE.md
